absl/__init__.py
absl/_collections_abc.py
absl/_enum_module.py
absl/app.py
absl/command_name.py
absl/flags/__init__.py
absl/flags/_argument_parser.py
absl/flags/_defines.py
absl/flags/_exceptions.py
absl/flags/_flag.py
absl/flags/_flagvalues.py
absl/flags/_helpers.py
absl/flags/_validators.py
absl/flags/_validators_classes.py
absl/flags/argparse_flags.py
absl/logging/__init__.py
absl/logging/converter.py
absl/testing/__init__.py
absl/testing/_bazelize_command.py
absl/testing/_parameterized_async.py
absl/testing/_pretty_print_reporter.py
absl/testing/absltest.py
absl/testing/flagsaver.py
absl/testing/parameterized.py
absl/testing/xml_reporter.py
absl/third_party/__init__.py
absl/third_party/unittest3_backport/__init__.py
absl/third_party/unittest3_backport/case.py
absl/third_party/unittest3_backport/result.py
absl_py-0.14.1.dist-info/AUTHORS
absl_py-0.14.1.dist-info/LICENSE
absl_py-0.14.1.dist-info/METADATA
absl_py-0.14.1.dist-info/WHEEL
absl_py-0.14.1.dist-info/top_level.txt
absl_py-0.14.1.dist-info/RECORD
